tensorscope/__init__.py
tensorscope/analysis.py
tensorscope/elem_count.py
tensorscope/elem_count_handles.py
tensorscope-1.0.1.dist-info/METADATA
tensorscope-1.0.1.dist-info/WHEEL
tensorscope-1.0.1.dist-info/top_level.txt
tensorscope-1.0.1.dist-info/RECORD
