Metadata-Version: 2.4
Name: tensorscope
Version: 1.0.1
Summary: Analyze PyTorch models to determine limiting factors in each layer.
Project-URL: Repository, https://github.com/carsonjf8/Tensorscope
Requires-Python: >=3.8
Requires-Dist: torch>=2.0.0
Requires-Dist: fvcore>=0.1.5.post20221221
Requires-Dist: tabulate>=0.9.0
